{ "columns":56,
 "image":"tileset.png",
 "imageheight":576,
 "imagewidth":448,
 "margin":0,
 "name":"tileset",
 "spacing":0,
 "tilecount":4032,
 "tiledversion":"1.9.0",
 "tileheight":8,
 "tiles":[
        {
         "id":336,
         "objectgroup":
            {
             "draworder":"index",
             "id":2,
             "name":"",
             "objects":[
                    {
                     "class":"",
                     "height":8,
                     "id":1,
                     "name":"",
                     "rotation":0,
                     "visible":true,
                     "width":8,
                     "x":0,
                     "y":0
                    }, 
                    {
                     "class":"",
                     "height":8,
                     "id":2,
                     "name":"",
                     "rotation":0,
                     "visible":false,
                     "width":8,
                     "x":0,
                     "y":0
                    }],
             "opacity":1,
             "type":"objectgroup",
             "visible":true,
             "x":0,
             "y":0
            }
        }, 
        {
         "id":337,
         "objectgroup":
            {
             "draworder":"index",
             "id":2,
             "name":"",
             "objects":[
                    {
                     "class":"",
                     "height":8,
                     "id":1,
                     "name":"",
                     "rotation":0,
                     "visible":true,
                     "width":8,
                     "x":0,
                     "y":0
                    }],
             "opacity":1,
             "type":"objectgroup",
             "visible":true,
             "x":0,
             "y":0
            }
        }, 
        {
         "id":362,
         "objectgroup":
            {
             "draworder":"index",
             "id":2,
             "name":"",
             "objects":[
                    {
                     "class":"",
                     "height":8,
                     "id":1,
                     "name":"",
                     "rotation":0,
                     "visible":true,
                     "width":8,
                     "x":0,
                     "y":0
                    }, 
                    {
                     "class":"",
                     "height":8,
                     "id":2,
                     "name":"",
                     "rotation":0,
                     "visible":true,
                     "width":8,
                     "x":0,
                     "y":0
                    }],
             "opacity":1,
             "type":"objectgroup",
             "visible":true,
             "x":0,
             "y":0
            }
        }, 
        {
         "id":363,
         "objectgroup":
            {
             "draworder":"index",
             "id":2,
             "name":"",
             "objects":[
                    {
                     "class":"",
                     "height":8,
                     "id":1,
                     "name":"",
                     "rotation":0,
                     "visible":true,
                     "width":8,
                     "x":0,
                     "y":0
                    }],
             "opacity":1,
             "type":"objectgroup",
             "visible":true,
             "x":0,
             "y":0
            }
        }, 
        {
         "id":364,
         "objectgroup":
            {
             "draworder":"index",
             "id":2,
             "name":"",
             "objects":[
                    {
                     "class":"",
                     "height":8,
                     "id":1,
                     "name":"",
                     "rotation":0,
                     "visible":true,
                     "width":8,
                     "x":0,
                     "y":0
                    }],
             "opacity":1,
             "type":"objectgroup",
             "visible":true,
             "x":0,
             "y":0
            }
        }, 
        {
         "id":365,
         "objectgroup":
            {
             "draworder":"index",
             "id":2,
             "name":"",
             "objects":[
                    {
                     "class":"",
                     "height":8,
                     "id":1,
                     "name":"",
                     "rotation":0,
                     "visible":true,
                     "width":8,
                     "x":0,
                     "y":0
                    }],
             "opacity":1,
             "type":"objectgroup",
             "visible":true,
             "x":0,
             "y":0
            }
        }, 
        {
         "id":390,
         "objectgroup":
            {
             "draworder":"index",
             "id":2,
             "name":"",
             "objects":[
                    {
                     "class":"",
                     "height":8,
                     "id":1,
                     "name":"",
                     "rotation":0,
                     "visible":true,
                     "width":8,
                     "x":0,
                     "y":0
                    }],
             "opacity":1,
             "type":"objectgroup",
             "visible":true,
             "x":0,
             "y":0
            }
        }, 
        {
         "id":391,
         "objectgroup":
            {
             "draworder":"index",
             "id":2,
             "name":"",
             "objects":[
                    {
                     "class":"",
                     "height":8,
                     "id":1,
                     "name":"",
                     "rotation":0,
                     "visible":true,
                     "width":8,
                     "x":0,
                     "y":0
                    }],
             "opacity":1,
             "type":"objectgroup",
             "visible":true,
             "x":0,
             "y":0
            }
        }, 
        {
         "id":392,
         "objectgroup":
            {
             "draworder":"index",
             "id":2,
             "name":"",
             "objects":[
                    {
                     "class":"",
                     "height":8,
                     "id":1,
                     "name":"",
                     "rotation":0,
                     "visible":true,
                     "width":8,
                     "x":0,
                     "y":0
                    }],
             "opacity":1,
             "type":"objectgroup",
             "visible":true,
             "x":0,
             "y":0
            }
        }, 
        {
         "id":419,
         "objectgroup":
            {
             "draworder":"index",
             "id":2,
             "name":"",
             "objects":[
                    {
                     "class":"",
                     "height":8,
                     "id":1,
                     "name":"",
                     "rotation":0,
                     "visible":true,
                     "width":8,
                     "x":0,
                     "y":0
                    }],
             "opacity":1,
             "type":"objectgroup",
             "visible":true,
             "x":0,
             "y":0
            }
        }, 
        {
         "id":420,
         "objectgroup":
            {
             "draworder":"index",
             "id":2,
             "name":"",
             "objects":[
                    {
                     "class":"",
                     "height":8,
                     "id":1,
                     "name":"",
                     "rotation":0,
                     "visible":true,
                     "width":8,
                     "x":0,
                     "y":0
                    }],
             "opacity":1,
             "type":"objectgroup",
             "visible":true,
             "x":0,
             "y":0
            }
        }, 
        {
         "id":447,
         "objectgroup":
            {
             "draworder":"index",
             "id":2,
             "name":"",
             "objects":[
                    {
                     "class":"",
                     "height":8,
                     "id":1,
                     "name":"",
                     "rotation":0,
                     "visible":true,
                     "width":8,
                     "x":0,
                     "y":0
                    }],
             "opacity":1,
             "type":"objectgroup",
             "visible":true,
             "x":0,
             "y":0
            }
        }, 
        {
         "id":448,
         "objectgroup":
            {
             "draworder":"index",
             "id":2,
             "name":"",
             "objects":[
                    {
                     "class":"",
                     "height":8,
                     "id":1,
                     "name":"",
                     "rotation":0,
                     "visible":true,
                     "width":8,
                     "x":0,
                     "y":0
                    }],
             "opacity":1,
             "type":"objectgroup",
             "visible":true,
             "x":0,
             "y":0
            }
        }, 
        {
         "id":475,
         "objectgroup":
            {
             "draworder":"index",
             "id":2,
             "name":"",
             "objects":[
                    {
                     "class":"",
                     "height":8,
                     "id":1,
                     "name":"",
                     "rotation":0,
                     "visible":true,
                     "width":8,
                     "x":0,
                     "y":0
                    }],
             "opacity":1,
             "type":"objectgroup",
             "visible":true,
             "x":0,
             "y":0
            }
        }, 
        {
         "id":476,
         "objectgroup":
            {
             "draworder":"index",
             "id":2,
             "name":"",
             "objects":[
                    {
                     "class":"",
                     "height":8,
                     "id":1,
                     "name":"",
                     "rotation":0,
                     "visible":true,
                     "width":8,
                     "x":0,
                     "y":0
                    }],
             "opacity":1,
             "type":"objectgroup",
             "visible":true,
             "x":0,
             "y":0
            }
        }, 
        {
         "id":504,
         "objectgroup":
            {
             "draworder":"index",
             "id":2,
             "name":"",
             "objects":[
                    {
                     "class":"",
                     "height":8,
                     "id":1,
                     "name":"",
                     "rotation":0,
                     "visible":true,
                     "width":8,
                     "x":0,
                     "y":0
                    }],
             "opacity":1,
             "type":"objectgroup",
             "visible":true,
             "x":0,
             "y":0
            }
        }, 
        {
         "id":560,
         "objectgroup":
            {
             "draworder":"index",
             "id":2,
             "name":"",
             "objects":[
                    {
                     "class":"",
                     "height":8,
                     "id":1,
                     "name":"",
                     "rotation":0,
                     "visible":true,
                     "width":8,
                     "x":0,
                     "y":0
                    }],
             "opacity":1,
             "type":"objectgroup",
             "visible":true,
             "x":0,
             "y":0
            }
        }, 
        {
         "id":616,
         "objectgroup":
            {
             "draworder":"index",
             "id":2,
             "name":"",
             "objects":[
                    {
                     "class":"",
                     "height":8,
                     "id":1,
                     "name":"",
                     "rotation":0,
                     "visible":true,
                     "width":8,
                     "x":0,
                     "y":0
                    }],
             "opacity":1,
             "type":"objectgroup",
             "visible":true,
             "x":0,
             "y":0
            }
        }, 
        {
         "id":649,
         "objectgroup":
            {
             "draworder":"index",
             "id":2,
             "name":"",
             "objects":[
                    {
                     "class":"",
                     "height":8,
                     "id":1,
                     "name":"",
                     "rotation":0,
                     "visible":true,
                     "width":8,
                     "x":0,
                     "y":0
                    }],
             "opacity":1,
             "type":"objectgroup",
             "visible":true,
             "x":0,
             "y":0
            }
        }, 
        {
         "id":650,
         "objectgroup":
            {
             "draworder":"index",
             "id":2,
             "name":"",
             "objects":[
                    {
                     "class":"",
                     "height":8,
                     "id":1,
                     "name":"",
                     "rotation":0,
                     "visible":true,
                     "width":8,
                     "x":0,
                     "y":0
                    }],
             "opacity":1,
             "type":"objectgroup",
             "visible":true,
             "x":0,
             "y":0
            }
        }, 
        {
         "id":651,
         "objectgroup":
            {
             "draworder":"index",
             "id":2,
             "name":"",
             "objects":[
                    {
                     "class":"",
                     "height":0,
                     "id":1,
                     "name":"",
                     "rotation":0,
                     "visible":true,
                     "width":0,
                     "x":3.91304347826087,
                     "y":3.39130434782609
                    }],
             "opacity":1,
             "type":"objectgroup",
             "visible":true,
             "x":0,
             "y":0
            }
        }, 
        {
         "id":656,
         "objectgroup":
            {
             "draworder":"index",
             "id":2,
             "name":"",
             "objects":[
                    {
                     "class":"",
                     "height":8,
                     "id":1,
                     "name":"",
                     "rotation":0,
                     "visible":true,
                     "width":8,
                     "x":0,
                     "y":0
                    }],
             "opacity":1,
             "type":"objectgroup",
             "visible":true,
             "x":0,
             "y":0
            }
        }, 
        {
         "id":672,
         "objectgroup":
            {
             "draworder":"index",
             "id":2,
             "name":"",
             "objects":[
                    {
                     "class":"",
                     "height":8,
                     "id":1,
                     "name":"",
                     "rotation":0,
                     "visible":true,
                     "width":8,
                     "x":0,
                     "y":0
                    }],
             "opacity":1,
             "type":"objectgroup",
             "visible":true,
             "x":0,
             "y":0
            }
        }, 
        {
         "id":728,
         "objectgroup":
            {
             "draworder":"index",
             "id":2,
             "name":"",
             "objects":[
                    {
                     "class":"",
                     "height":8,
                     "id":1,
                     "name":"",
                     "rotation":0,
                     "visible":true,
                     "width":8,
                     "x":0,
                     "y":0
                    }],
             "opacity":1,
             "type":"objectgroup",
             "visible":true,
             "x":0,
             "y":0
            }
        }, 
        {
         "id":784,
         "objectgroup":
            {
             "draworder":"index",
             "id":2,
             "name":"",
             "objects":[
                    {
                     "class":"",
                     "height":8,
                     "id":1,
                     "name":"",
                     "rotation":0,
                     "visible":true,
                     "width":8,
                     "x":0,
                     "y":0
                    }],
             "opacity":1,
             "type":"objectgroup",
             "visible":true,
             "x":0,
             "y":0
            }
        }, 
        {
         "id":811,
         "objectgroup":
            {
             "draworder":"index",
             "id":2,
             "name":"",
             "objects":[
                    {
                     "class":"",
                     "height":8,
                     "id":1,
                     "name":"",
                     "rotation":0,
                     "visible":true,
                     "width":8,
                     "x":0,
                     "y":0
                    }],
             "opacity":1,
             "type":"objectgroup",
             "visible":true,
             "x":0,
             "y":0
            }
        }, 
        {
         "id":812,
         "objectgroup":
            {
             "draworder":"index",
             "id":2,
             "name":"",
             "objects":[
                    {
                     "class":"",
                     "height":8,
                     "id":1,
                     "name":"",
                     "rotation":0,
                     "visible":true,
                     "width":8,
                     "x":0,
                     "y":0
                    }],
             "opacity":1,
             "type":"objectgroup",
             "visible":true,
             "x":0,
             "y":0
            }
        }, 
        {
         "id":818,
         "objectgroup":
            {
             "draworder":"index",
             "id":2,
             "name":"",
             "objects":[
                    {
                     "class":"",
                     "height":8,
                     "id":1,
                     "name":"",
                     "rotation":0,
                     "visible":true,
                     "width":8,
                     "x":0,
                     "y":0
                    }],
             "opacity":1,
             "type":"objectgroup",
             "visible":true,
             "x":0,
             "y":0
            }
        }, 
        {
         "id":1344,
         "objectgroup":
            {
             "draworder":"index",
             "id":2,
             "name":"",
             "objects":[
                    {
                     "class":"",
                     "height":8,
                     "id":1,
                     "name":"",
                     "rotation":0,
                     "visible":true,
                     "width":8,
                     "x":0,
                     "y":0
                    }, 
                    {
                     "class":"",
                     "height":8,
                     "id":2,
                     "name":"",
                     "rotation":0,
                     "visible":true,
                     "width":8,
                     "x":0,
                     "y":0
                    }],
             "opacity":1,
             "type":"objectgroup",
             "visible":true,
             "x":0,
             "y":0
            }
        }, 
        {
         "id":1399,
         "objectgroup":
            {
             "draworder":"index",
             "id":2,
             "name":"",
             "objects":[
                    {
                     "class":"",
                     "height":8,
                     "id":1,
                     "name":"",
                     "rotation":0,
                     "visible":true,
                     "width":8,
                     "x":0,
                     "y":0
                    }, 
                    {
                     "class":"",
                     "height":8,
                     "id":2,
                     "name":"",
                     "rotation":0,
                     "visible":true,
                     "width":8,
                     "x":0,
                     "y":0
                    }],
             "opacity":1,
             "type":"objectgroup",
             "visible":true,
             "x":0,
             "y":0
            }
        }, 
        {
         "id":1400,
         "objectgroup":
            {
             "draworder":"index",
             "id":2,
             "name":"",
             "objects":[
                    {
                     "class":"",
                     "height":8,
                     "id":1,
                     "name":"",
                     "rotation":0,
                     "visible":true,
                     "width":8,
                     "x":0,
                     "y":0
                    }, 
                    {
                     "class":"",
                     "height":8,
                     "id":2,
                     "name":"",
                     "rotation":0,
                     "visible":true,
                     "width":8,
                     "x":0,
                     "y":0
                    }],
             "opacity":1,
             "type":"objectgroup",
             "visible":true,
             "x":0,
             "y":0
            }
        }, 
        {
         "id":1401,
         "objectgroup":
            {
             "draworder":"index",
             "id":2,
             "name":"",
             "objects":[
                    {
                     "class":"",
                     "height":8,
                     "id":1,
                     "name":"",
                     "rotation":0,
                     "visible":true,
                     "width":8,
                     "x":0,
                     "y":0
                    }, 
                    {
                     "class":"",
                     "height":8,
                     "id":2,
                     "name":"",
                     "rotation":0,
                     "visible":true,
                     "width":8,
                     "x":0,
                     "y":0
                    }],
             "opacity":1,
             "type":"objectgroup",
             "visible":true,
             "x":0,
             "y":0
            }
        }, 
        {
         "id":1402,
         "objectgroup":
            {
             "draworder":"index",
             "id":2,
             "name":"",
             "objects":[
                    {
                     "class":"",
                     "height":8,
                     "id":1,
                     "name":"",
                     "rotation":0,
                     "visible":true,
                     "width":8,
                     "x":0,
                     "y":0
                    }],
             "opacity":1,
             "type":"objectgroup",
             "visible":true,
             "x":0,
             "y":0
            }
        }, 
        {
         "id":1410,
         "objectgroup":
            {
             "draworder":"index",
             "id":2,
             "name":"",
             "objects":[
                    {
                     "class":"",
                     "height":8,
                     "id":1,
                     "name":"",
                     "rotation":0,
                     "visible":true,
                     "width":8,
                     "x":0,
                     "y":0
                    }, 
                    {
                     "class":"",
                     "height":8,
                     "id":2,
                     "name":"",
                     "rotation":0,
                     "visible":true,
                     "width":8,
                     "x":0,
                     "y":0
                    }, 
                    {
                     "class":"",
                     "height":8,
                     "id":3,
                     "name":"",
                     "rotation":0,
                     "visible":true,
                     "width":8,
                     "x":0,
                     "y":0
                    }],
             "opacity":1,
             "type":"objectgroup",
             "visible":true,
             "x":0,
             "y":0
            }
        }, 
        {
         "id":1445,
         "objectgroup":
            {
             "draworder":"index",
             "id":2,
             "name":"",
             "objects":[
                    {
                     "class":"",
                     "height":8,
                     "id":1,
                     "name":"",
                     "rotation":0,
                     "visible":true,
                     "width":8,
                     "x":0,
                     "y":0
                    }],
             "opacity":1,
             "type":"objectgroup",
             "visible":true,
             "x":0,
             "y":0
            }
        }, 
        {
         "id":1454,
         "objectgroup":
            {
             "draworder":"index",
             "id":2,
             "name":"",
             "objects":[
                    {
                     "class":"",
                     "height":8,
                     "id":1,
                     "name":"",
                     "rotation":0,
                     "visible":true,
                     "width":8,
                     "x":0,
                     "y":0
                    }, 
                    {
                     "class":"",
                     "height":8,
                     "id":2,
                     "name":"",
                     "rotation":0,
                     "visible":true,
                     "width":8,
                     "x":0,
                     "y":0
                    }],
             "opacity":1,
             "type":"objectgroup",
             "visible":true,
             "x":0,
             "y":0
            }
        }, 
        {
         "id":1455,
         "objectgroup":
            {
             "draworder":"index",
             "id":2,
             "name":"",
             "objects":[
                    {
                     "class":"",
                     "height":8,
                     "id":1,
                     "name":"",
                     "rotation":0,
                     "visible":true,
                     "width":8,
                     "x":0,
                     "y":0
                    }, 
                    {
                     "class":"",
                     "height":8,
                     "id":2,
                     "name":"",
                     "rotation":0,
                     "visible":true,
                     "width":8,
                     "x":0,
                     "y":0
                    }],
             "opacity":1,
             "type":"objectgroup",
             "visible":true,
             "x":0,
             "y":0
            }
        }, 
        {
         "id":1522,
         "objectgroup":
            {
             "draworder":"index",
             "id":2,
             "name":"",
             "objects":[
                    {
                     "class":"",
                     "height":8,
                     "id":1,
                     "name":"",
                     "rotation":0,
                     "visible":true,
                     "width":8,
                     "x":0,
                     "y":0
                    }],
             "opacity":1,
             "type":"objectgroup",
             "visible":true,
             "x":0,
             "y":0
            }
        }, 
        {
         "id":1757,
         "objectgroup":
            {
             "draworder":"index",
             "id":2,
             "name":"",
             "objects":[
                    {
                     "class":"",
                     "height":8,
                     "id":1,
                     "name":"",
                     "rotation":0,
                     "visible":true,
                     "width":8,
                     "x":0,
                     "y":0
                    }],
             "opacity":1,
             "type":"objectgroup",
             "visible":true,
             "x":0,
             "y":0
            }
        }, 
        {
         "id":1770,
         "objectgroup":
            {
             "draworder":"index",
             "id":2,
             "name":"",
             "objects":[
                    {
                     "class":"",
                     "height":8,
                     "id":1,
                     "name":"",
                     "rotation":0,
                     "visible":true,
                     "width":8,
                     "x":0,
                     "y":0
                    }],
             "opacity":1,
             "type":"objectgroup",
             "visible":true,
             "x":0,
             "y":0
            }
        }, 
        {
         "id":1802,
         "objectgroup":
            {
             "draworder":"index",
             "id":2,
             "name":"",
             "objects":[
                    {
                     "class":"",
                     "height":8,
                     "id":1,
                     "name":"",
                     "rotation":0,
                     "visible":true,
                     "width":8,
                     "x":0,
                     "y":0
                    }],
             "opacity":1,
             "type":"objectgroup",
             "visible":true,
             "x":0,
             "y":0
            }
        }, 
        {
         "id":1837,
         "objectgroup":
            {
             "draworder":"index",
             "id":2,
             "name":"",
             "objects":[
                    {
                     "class":"",
                     "height":8,
                     "id":1,
                     "name":"",
                     "rotation":0,
                     "visible":true,
                     "width":8,
                     "x":0,
                     "y":0
                    }],
             "opacity":1,
             "type":"objectgroup",
             "visible":true,
             "x":0,
             "y":0
            }
        }, 
        {
         "id":2082,
         "objectgroup":
            {
             "draworder":"index",
             "id":2,
             "name":"",
             "objects":[
                    {
                     "class":"",
                     "height":8,
                     "id":1,
                     "name":"",
                     "rotation":0,
                     "visible":true,
                     "width":8,
                     "x":0,
                     "y":0
                    }],
             "opacity":1,
             "type":"objectgroup",
             "visible":true,
             "x":0,
             "y":0
            }
        }, 
        {
         "id":2117,
         "objectgroup":
            {
             "draworder":"index",
             "id":2,
             "name":"",
             "objects":[
                    {
                     "class":"",
                     "height":8,
                     "id":1,
                     "name":"",
                     "rotation":0,
                     "visible":true,
                     "width":8,
                     "x":0,
                     "y":0
                    }],
             "opacity":1,
             "type":"objectgroup",
             "visible":true,
             "x":0,
             "y":0
            }
        }, 
        {
         "id":2138,
         "objectgroup":
            {
             "draworder":"index",
             "id":2,
             "name":"",
             "objects":[
                    {
                     "class":"",
                     "height":8,
                     "id":1,
                     "name":"",
                     "rotation":0,
                     "visible":true,
                     "width":8,
                     "x":0,
                     "y":0
                    }],
             "opacity":1,
             "type":"objectgroup",
             "visible":true,
             "x":0,
             "y":0
            }
        }, 
        {
         "id":2149,
         "objectgroup":
            {
             "draworder":"index",
             "id":2,
             "name":"",
             "objects":[
                    {
                     "class":"",
                     "height":8,
                     "id":1,
                     "name":"",
                     "rotation":0,
                     "visible":true,
                     "width":8,
                     "x":0,
                     "y":0
                    }],
             "opacity":1,
             "type":"objectgroup",
             "visible":true,
             "x":0,
             "y":0
            }
        }, 
        {
         "id":2162,
         "objectgroup":
            {
             "draworder":"index",
             "id":2,
             "name":"",
             "objects":[
                    {
                     "class":"",
                     "height":8,
                     "id":1,
                     "name":"",
                     "rotation":0,
                     "visible":true,
                     "width":8,
                     "x":0,
                     "y":0
                    }],
             "opacity":1,
             "type":"objectgroup",
             "visible":true,
             "x":0,
             "y":0
            }
        }, 
        {
         "id":2464,
         "objectgroup":
            {
             "draworder":"index",
             "id":2,
             "name":"",
             "objects":[
                    {
                     "class":"",
                     "height":8,
                     "id":1,
                     "name":"",
                     "rotation":0,
                     "visible":true,
                     "width":8,
                     "x":0,
                     "y":0
                    }],
             "opacity":1,
             "type":"objectgroup",
             "visible":true,
             "x":0,
             "y":0
            }
        }, 
        {
         "id":2465,
         "objectgroup":
            {
             "draworder":"index",
             "id":2,
             "name":"",
             "objects":[
                    {
                     "class":"",
                     "height":8,
                     "id":1,
                     "name":"",
                     "rotation":0,
                     "visible":true,
                     "width":8,
                     "x":0,
                     "y":0
                    }],
             "opacity":1,
             "type":"objectgroup",
             "visible":true,
             "x":0,
             "y":0
            }
        }, 
        {
         "id":2474,
         "objectgroup":
            {
             "draworder":"index",
             "id":2,
             "name":"",
             "objects":[
                    {
                     "class":"",
                     "height":8,
                     "id":1,
                     "name":"",
                     "rotation":0,
                     "visible":true,
                     "width":8,
                     "x":0,
                     "y":0
                    }],
             "opacity":1,
             "type":"objectgroup",
             "visible":true,
             "x":0,
             "y":0
            }
        }, 
        {
         "id":2509,
         "objectgroup":
            {
             "draworder":"index",
             "id":2,
             "name":"",
             "objects":[
                    {
                     "class":"",
                     "height":8,
                     "id":1,
                     "name":"",
                     "rotation":0,
                     "visible":true,
                     "width":8,
                     "x":0,
                     "y":0
                    }],
             "opacity":1,
             "type":"objectgroup",
             "visible":true,
             "x":0,
             "y":0
            }
        }, 
        {
         "id":2518,
         "objectgroup":
            {
             "draworder":"index",
             "id":2,
             "name":"",
             "objects":[
                    {
                     "class":"",
                     "height":8,
                     "id":1,
                     "name":"",
                     "rotation":0,
                     "visible":true,
                     "width":8,
                     "x":0,
                     "y":0
                    }],
             "opacity":1,
             "type":"objectgroup",
             "visible":true,
             "x":0,
             "y":0
            }
        }, 
        {
         "id":2519,
         "objectgroup":
            {
             "draworder":"index",
             "id":2,
             "name":"",
             "objects":[
                    {
                     "class":"",
                     "height":8,
                     "id":1,
                     "name":"",
                     "rotation":0,
                     "visible":true,
                     "width":8,
                     "x":0,
                     "y":0
                    }],
             "opacity":1,
             "type":"objectgroup",
             "visible":true,
             "x":0,
             "y":0
            }
        }, 
        {
         "id":2520,
         "objectgroup":
            {
             "draworder":"index",
             "id":2,
             "name":"",
             "objects":[
                    {
                     "class":"",
                     "height":8,
                     "id":1,
                     "name":"",
                     "rotation":0,
                     "visible":true,
                     "width":8,
                     "x":0,
                     "y":0
                    }],
             "opacity":1,
             "type":"objectgroup",
             "visible":true,
             "x":0,
             "y":0
            }
        }, 
        {
         "id":2575,
         "objectgroup":
            {
             "draworder":"index",
             "id":2,
             "name":"",
             "objects":[
                    {
                     "class":"",
                     "height":8,
                     "id":1,
                     "name":"",
                     "rotation":0,
                     "visible":true,
                     "width":8,
                     "x":0,
                     "y":0
                    }],
             "opacity":1,
             "type":"objectgroup",
             "visible":true,
             "x":0,
             "y":0
            }
        }, 
        {
         "id":3024,
         "objectgroup":
            {
             "draworder":"index",
             "id":2,
             "name":"",
             "objects":[
                    {
                     "class":"",
                     "height":8,
                     "id":1,
                     "name":"",
                     "rotation":0,
                     "visible":true,
                     "width":8,
                     "x":0,
                     "y":0
                    }],
             "opacity":1,
             "type":"objectgroup",
             "visible":true,
             "x":0,
             "y":0
            }
        }, 
        {
         "id":3079,
         "objectgroup":
            {
             "draworder":"index",
             "id":2,
             "name":"",
             "objects":[
                    {
                     "class":"",
                     "height":8,
                     "id":1,
                     "name":"",
                     "rotation":0,
                     "visible":true,
                     "width":8,
                     "x":0,
                     "y":0
                    }],
             "opacity":1,
             "type":"objectgroup",
             "visible":true,
             "x":0,
             "y":0
            }
        }, 
        {
         "id":3081,
         "objectgroup":
            {
             "draworder":"index",
             "id":2,
             "name":"",
             "objects":[
                    {
                     "class":"",
                     "height":8,
                     "id":1,
                     "name":"",
                     "rotation":0,
                     "visible":true,
                     "width":8,
                     "x":0,
                     "y":0
                    }],
             "opacity":1,
             "type":"objectgroup",
             "visible":true,
             "x":0,
             "y":0
            }
        }, 
        {
         "id":3134,
         "objectgroup":
            {
             "draworder":"index",
             "id":2,
             "name":"",
             "objects":[
                    {
                     "class":"",
                     "height":8,
                     "id":1,
                     "name":"",
                     "rotation":0,
                     "visible":true,
                     "width":8,
                     "x":0,
                     "y":0
                    }],
             "opacity":1,
             "type":"objectgroup",
             "visible":true,
             "x":0,
             "y":0
            }
        }, 
        {
         "id":3135,
         "objectgroup":
            {
             "draworder":"index",
             "id":2,
             "name":"",
             "objects":[
                    {
                     "class":"",
                     "height":8,
                     "id":1,
                     "name":"",
                     "rotation":0,
                     "visible":true,
                     "width":8,
                     "x":0,
                     "y":0
                    }],
             "opacity":1,
             "type":"objectgroup",
             "visible":true,
             "x":0,
             "y":0
            }
        }, 
        {
         "id":3137,
         "objectgroup":
            {
             "draworder":"index",
             "id":2,
             "name":"",
             "objects":[
                    {
                     "class":"",
                     "height":8,
                     "id":1,
                     "name":"",
                     "rotation":0,
                     "visible":true,
                     "width":8,
                     "x":0,
                     "y":0
                    }],
             "opacity":1,
             "type":"objectgroup",
             "visible":true,
             "x":0,
             "y":0
            }
        }, 
        {
         "id":3157,
         "objectgroup":
            {
             "draworder":"index",
             "id":2,
             "name":"",
             "objects":[
                    {
                     "class":"",
                     "height":8,
                     "id":1,
                     "name":"",
                     "rotation":0,
                     "visible":true,
                     "width":8,
                     "x":0,
                     "y":0
                    }],
             "opacity":1,
             "type":"objectgroup",
             "visible":true,
             "x":0,
             "y":0
            }
        }, 
        {
         "id":3162,
         "objectgroup":
            {
             "draworder":"index",
             "id":2,
             "name":"",
             "objects":[
                    {
                     "class":"",
                     "height":8,
                     "id":1,
                     "name":"",
                     "rotation":0,
                     "visible":true,
                     "width":8,
                     "x":0,
                     "y":0
                    }],
             "opacity":1,
             "type":"objectgroup",
             "visible":true,
             "x":0,
             "y":0
            }
        }, 
        {
         "id":3165,
         "objectgroup":
            {
             "draworder":"index",
             "id":2,
             "name":"",
             "objects":[
                    {
                     "class":"",
                     "height":8,
                     "id":1,
                     "name":"",
                     "rotation":0,
                     "visible":true,
                     "width":8,
                     "x":0,
                     "y":0
                    }],
             "opacity":1,
             "type":"objectgroup",
             "visible":true,
             "x":0,
             "y":0
            }
        }, 
        {
         "id":3190,
         "objectgroup":
            {
             "draworder":"index",
             "id":2,
             "name":"",
             "objects":[
                    {
                     "class":"",
                     "height":8,
                     "id":1,
                     "name":"",
                     "rotation":0,
                     "visible":true,
                     "width":8,
                     "x":0,
                     "y":0
                    }],
             "opacity":1,
             "type":"objectgroup",
             "visible":true,
             "x":0,
             "y":0
            }
        }, 
        {
         "id":3191,
         "objectgroup":
            {
             "draworder":"index",
             "id":2,
             "name":"",
             "objects":[
                    {
                     "class":"",
                     "height":8,
                     "id":1,
                     "name":"",
                     "rotation":0,
                     "visible":true,
                     "width":8,
                     "x":0,
                     "y":0
                    }],
             "opacity":1,
             "type":"objectgroup",
             "visible":true,
             "x":0,
             "y":0
            }
        }, 
        {
         "id":3192,
         "objectgroup":
            {
             "draworder":"index",
             "id":2,
             "name":"",
             "objects":[
                    {
                     "class":"",
                     "height":8,
                     "id":1,
                     "name":"",
                     "rotation":0,
                     "visible":true,
                     "width":8,
                     "x":0,
                     "y":0
                    }],
             "opacity":1,
             "type":"objectgroup",
             "visible":true,
             "x":0,
             "y":0
            }
        }, 
        {
         "id":3219,
         "objectgroup":
            {
             "draworder":"index",
             "id":2,
             "name":"",
             "objects":[
                    {
                     "class":"",
                     "height":8,
                     "id":1,
                     "name":"",
                     "rotation":0,
                     "visible":true,
                     "width":8,
                     "x":0,
                     "y":0
                    }],
             "opacity":1,
             "type":"objectgroup",
             "visible":true,
             "x":0,
             "y":0
            }
        }, 
        {
         "id":3220,
         "objectgroup":
            {
             "draworder":"index",
             "id":2,
             "name":"",
             "objects":[
                    {
                     "class":"",
                     "height":8,
                     "id":1,
                     "name":"",
                     "rotation":0,
                     "visible":true,
                     "width":8,
                     "x":0,
                     "y":0
                    }],
             "opacity":1,
             "type":"objectgroup",
             "visible":true,
             "x":0,
             "y":0
            }
        }, 
        {
         "id":3247,
         "objectgroup":
            {
             "draworder":"index",
             "id":2,
             "name":"",
             "objects":[
                    {
                     "class":"",
                     "height":8,
                     "id":1,
                     "name":"",
                     "rotation":0,
                     "visible":true,
                     "width":8,
                     "x":0,
                     "y":0
                    }],
             "opacity":1,
             "type":"objectgroup",
             "visible":true,
             "x":0,
             "y":0
            }
        }, 
        {
         "id":3399,
         "objectgroup":
            {
             "draworder":"index",
             "id":2,
             "name":"",
             "objects":[
                    {
                     "class":"",
                     "height":8,
                     "id":1,
                     "name":"",
                     "rotation":0,
                     "visible":true,
                     "width":8,
                     "x":0,
                     "y":0
                    }],
             "opacity":1,
             "type":"objectgroup",
             "visible":true,
             "x":0,
             "y":0
            }
        }, 
        {
         "id":3400,
         "objectgroup":
            {
             "draworder":"index",
             "id":2,
             "name":"",
             "objects":[
                    {
                     "class":"",
                     "height":8,
                     "id":1,
                     "name":"",
                     "rotation":0,
                     "visible":true,
                     "width":8,
                     "x":0,
                     "y":0
                    }],
             "opacity":1,
             "type":"objectgroup",
             "visible":true,
             "x":0,
             "y":0
            }
        }, 
        {
         "id":3696,
         "objectgroup":
            {
             "draworder":"index",
             "id":2,
             "name":"",
             "objects":[
                    {
                     "class":"",
                     "height":8,
                     "id":1,
                     "name":"",
                     "rotation":0,
                     "visible":true,
                     "width":8,
                     "x":0,
                     "y":0
                    }],
             "opacity":1,
             "type":"objectgroup",
             "visible":true,
             "x":0,
             "y":0
            }
        }, 
        {
         "id":3751,
         "objectgroup":
            {
             "draworder":"index",
             "id":2,
             "name":"",
             "objects":[
                    {
                     "class":"",
                     "height":8,
                     "id":1,
                     "name":"",
                     "rotation":0,
                     "visible":true,
                     "width":8,
                     "x":0,
                     "y":0
                    }],
             "opacity":1,
             "type":"objectgroup",
             "visible":true,
             "x":0,
             "y":0
            }
        }, 
        {
         "id":3752,
         "objectgroup":
            {
             "draworder":"index",
             "id":2,
             "name":"",
             "objects":[
                    {
                     "class":"",
                     "height":8,
                     "id":1,
                     "name":"",
                     "rotation":0,
                     "visible":true,
                     "width":8,
                     "x":0,
                     "y":0
                    }],
             "opacity":1,
             "type":"objectgroup",
             "visible":true,
             "x":0,
             "y":0
            }
        }, 
        {
         "id":3753,
         "objectgroup":
            {
             "draworder":"index",
             "id":2,
             "name":"",
             "objects":[
                    {
                     "class":"",
                     "height":8,
                     "id":1,
                     "name":"",
                     "rotation":0,
                     "visible":true,
                     "width":8,
                     "x":0,
                     "y":0
                    }],
             "opacity":1,
             "type":"objectgroup",
             "visible":true,
             "x":0,
             "y":0
            }
        }, 
        {
         "id":3806,
         "objectgroup":
            {
             "draworder":"index",
             "id":2,
             "name":"",
             "objects":[
                    {
                     "class":"",
                     "height":8,
                     "id":1,
                     "name":"",
                     "rotation":0,
                     "visible":true,
                     "width":8,
                     "x":0,
                     "y":0
                    }],
             "opacity":1,
             "type":"objectgroup",
             "visible":true,
             "x":0,
             "y":0
            }
        }, 
        {
         "id":3807,
         "objectgroup":
            {
             "draworder":"index",
             "id":2,
             "name":"",
             "objects":[
                    {
                     "class":"",
                     "height":8,
                     "id":1,
                     "name":"",
                     "rotation":0,
                     "visible":true,
                     "width":8,
                     "x":0,
                     "y":0
                    }],
             "opacity":1,
             "type":"objectgroup",
             "visible":true,
             "x":0,
             "y":0
            }
        }],
 "tilewidth":8,
 "type":"tileset",
 "version":"1.8"
}